LICENSE
MANIFEST.in
README.md
setup.py
cppcloud/__init__.py
cppcloud/cliconfig.py
cppcloud/cloudapp.py
cppcloud/cloudconf.py
cppcloud/cloudinvoker.py
cppcloud/const.py
cppcloud/fileop.py
cppcloud/invokercli.py
cppcloud/provider.py
cppcloud/svrstat.py
cppcloud/tcpcli.py
cppcloud/tcpclient.py
cppcloud/tcpprovider.py
cppcloud.egg-info/PKG-INFO
cppcloud.egg-info/SOURCES.txt
cppcloud.egg-info/dependency_links.txt
cppcloud.egg-info/not-zip-safe
cppcloud.egg-info/requires.txt
cppcloud.egg-info/top_level.txt