Metadata-Version: 1.2
Name: cppcloud
Version: 1.0.2
Summary: CppCloud python3 客户端sdk
Home-page: UNKNOWN
Author: valueho
Author-email: hjl_mvp@126.com
License: Apache License
